{
  "方位": {
    "北": "正北方，坎水本位，主智慧学业、正财聚气、家宅根基，宜安静洁净、见静水旺财，忌路冲杂物压煞。",
    "东北": "东北方，艮土本位，为靠山子孙位，主人丁兴旺、事业有贵人、聚财守库，宜厚实稳重，忌低洼空缺。",
    "东": "正东方，震木本位，主事业生发、长子运势、文昌学业，利升职创业、才华施展，忌高楼遮挡气场。",
    "东南": "东南方，巽木财位，主四方人脉、经商偏财、机缘贵人，宜开阔通透、整洁明亮，主财源滚滚。",
    "南": "正南方，离火本位，主名声地位、事业声望、人际人缘，宜光亮开阔，主名利双收、前程明朗。",
    "西南": "西南方，坤土母位，主家庭和睦、长辈安康、田宅安稳，宜静不宜动，忌乱动工、尖角冲射。",
    "西": "正西方，兑金本位，主姻缘桃花、口才才艺、人际和合，气场清秀，利感情人缘、口碑扬名。",
    "西北": "西北方，乾金尊位，主父辈贵人、官运功名、家宅贵气，宜高大端正，主事业显贵、福泽绵长。"
  },
  "九星": {
    "贪": "贪狼星，九星首吉，五行属木，主正偏财、桃花人缘、机缘贵人，得位旺财旺丁、运势大顺。",
    "巨": "巨门星，五行属土，主田宅家业、口福安稳、稳重守成，利居家安稳、积蓄守财、家人安康。",
    "禄": "禄存星，半凶之星，五行属土，主运势起伏、人情是非、行事阻滞，宜低调守稳，避免冲动决策。",
    "文": "文曲星，智慧吉星，五行属水，主学业考试、才艺文采、心思灵动，利读书进修、技艺发展。",
    "武": "武曲星，正统吉星，五行属金，主官禄事业、正财稳健、刚毅成事，适合公职、实业、稳步求财。",
    "廉": "廉贞星，带煞凶星，五行属火，主是非官非、情绪波折、小灾小扰，布局需化解，不宜作为坐向主位。",
    "破": "破军星，变动凶星，五行属金，主破财损耗、格局翻新、人事变动，宜动中求变，守旧易有损失。",
    "辅": "左辅星，辅佐吉星，五行属土，主暗中贵人、逢凶化吉、家宅护佑，遇事多有助力帮扶。",
    "弼": "右弼星，助力吉星，五行属水，主机缘提携、人缘顺遂、隐性福气，易得贵人赏识、事事平顺。"
  }
}